cv_pruner/__init__.py
cv_pruner/cv_pruner.py
cv_pruner-0.0.1rc3.dist-info/LICENSE
cv_pruner-0.0.1rc3.dist-info/METADATA
cv_pruner-0.0.1rc3.dist-info/WHEEL
cv_pruner-0.0.1rc3.dist-info/top_level.txt
cv_pruner-0.0.1rc3.dist-info/RECORD
