Metadata-Version: 2.1
Name: cv-pruner
Version: 0.0.1rc3
Summary: Three-layer Pruning for Nested Cross-Validation to Accelerate Automated Hyperparameter Optimization for Embedded Feature Selection in High-Dimensional Data With Very Small Sample Sizes
Home-page: https://github.com/sigrun-may/cv-pruner
Author: Sigrun May
Author-email: s.may@ostfalia.de
Maintainer: Sigrun May
License: UNKNOWN
Project-URL: Bug Tracker, https://github.com/sigrun-may/cv-pruner/issues
Project-URL: Source Code, https://github.com/sigrun-may/cv-pruner
Project-URL: Contributing, https://github.com/sigrun-may/cv-pruner/blob/main/CONTRIBUTING.md
Project-URL: Code of Conduct, https://github.com/sigrun-may/cv-pruner/blob/main/CODE_OF_CONDUCT.md
Keywords: ml ai machine-learning hyperparameter-optimization high-dimensional data
Platform: UNKNOWN
Classifier: Development Status :: 3 - Alpha
Classifier: Intended Audience :: Science/Research
Classifier: Intended Audience :: Education
Classifier: Intended Audience :: Developers
Classifier: License :: OSI Approved :: MIT License
Classifier: Programming Language :: Python :: 3
Classifier: Programming Language :: Python :: 3.6
Classifier: Programming Language :: Python :: 3.7
Classifier: Programming Language :: Python :: 3.8
Classifier: Programming Language :: Python :: 3.9
Classifier: Programming Language :: Python :: 3 :: Only
Classifier: Topic :: Scientific/Engineering
Classifier: Topic :: Scientific/Engineering :: Artificial Intelligence
Classifier: Topic :: Scientific/Engineering :: Bio-Informatics
Classifier: Topic :: Scientific/Engineering :: Mathematics
Classifier: Topic :: Software Development
Classifier: Topic :: Software Development :: Libraries
Classifier: Topic :: Software Development :: Libraries :: Python Modules
Classifier: Operating System :: OS Independent
Requires-Python: >=3.6
License-File: LICENSE
Requires-Dist: numpy
Provides-Extra: checking
Requires-Dist: black ; extra == 'checking'
Requires-Dist: flake8 ; extra == 'checking'
Requires-Dist: isort ; extra == 'checking'
Requires-Dist: mdformat ; extra == 'checking'
Requires-Dist: pydocstyle ; extra == 'checking'
Requires-Dist: mypy ; extra == 'checking'
Requires-Dist: pylint ; extra == 'checking'
Requires-Dist: pylintfileheader ; extra == 'checking'
Provides-Extra: doc
Requires-Dist: sphinx ; extra == 'doc'
Requires-Dist: sphinx-rtd-theme ; extra == 'doc'
Requires-Dist: myst-parser ; extra == 'doc'
Requires-Dist: sphinx-copybutton ; extra == 'doc'
Provides-Extra: optional
Requires-Dist: pandas ; extra == 'optional'
Requires-Dist: optuna ; extra == 'optional'
Requires-Dist: scipy ; extra == 'optional'
Requires-Dist: lightgbm ; extra == 'optional'
Requires-Dist: tqdm ; extra == 'optional'
Requires-Dist: beautifulsoup4 ; extra == 'optional'
Provides-Extra: testing
Requires-Dist: pytest ; extra == 'testing'
